notebookAutomationUtils/__init__.py
notebookAutomationUtils/hockeyapp/__init__.py
notebookAutomationUtils/hockeyapp/api.py
notebookAutomationUtils/hockeyapp/budgeter.py
notebookAutomationUtils/hockeyapp/exceptions.py
notebookAutomationUtils/hockeyapp/models.py
notebookAutomationUtils/main/__init__.py
notebookAutomationUtils/main/automated_notebook.py
notebookAutomationUtils/main/automated_notebook_new.py
notebookAutomationUtils/main/generate_metrics.py
notebookAutomationUtils/tests/__init__.py
notebookAutomationUtils/tests/test_automated_notebook.py
notebookAutomationUtils/tests/test_generate_metrics.py
notebookAutomationUtils/tests/test_generate_notebook.py
notebookAutomationUtils/tests/test_graph_utils.py
notebookAutomationUtils/tests/test_hockey_utils.py
notebookAutomationUtils/tests/test_utils.py
notebookAutomationUtils/utils/__init__.py
notebookAutomationUtils/utils/graph_utils.py
notebookAutomationUtils/utils/hockey_utils.py
notebookAutomationUtils/utils/utils.py
notebookAutomationUtils-1.1.38.dist-info/LICENSE
notebookAutomationUtils-1.1.38.dist-info/METADATA
notebookAutomationUtils-1.1.38.dist-info/WHEEL
notebookAutomationUtils-1.1.38.dist-info/top_level.txt
notebookAutomationUtils-1.1.38.dist-info/RECORD
