Metadata-Version: 2.1
Name: notebookAutomationUtils
Version: 1.1.38
Summary: Tools for a notebook generator
Home-page: https://git.soma.salesforce.com/j-gao/notebook_automation_utils
Author: Tejal Parulekar, Jesse Gao
Author-email: tparulekar@salesforce.com, j.gao@salesforce.com
License: Private
Keywords: jupyter tools
Platform: UNKNOWN
Classifier: Programming Language :: Python :: 3
Classifier: Programming Language :: Python :: 3.4
Classifier: Programming Language :: Python :: 3.5
Classifier: Programming Language :: Python :: 3.6
Requires-Dist: setuptools (>=1.1.6)
Provides-Extra: dev
Requires-Dist: check-manifest ; extra == 'dev'
Provides-Extra: test
Requires-Dist: coverage ; extra == 'test'
